plrc/__init__.py
plrc/__main__.py
plrc/compiler/__init__.py
plrc/compiler/command.py
plrc/compiler/compiler.py
plrc/parser/__init__.py
plrc/parser/grammar.lark
plrc/parser/parser.py
plrc/transformer/__init__.py
plrc/transformer/binary/__init__.py
plrc/transformer/expr/__init__.py
plrc/transformer/functions/__init__.py
plrc/transformer/stmts/__init__.py
plrc/visitor/__init__.py
plrc-0.1.0.dist-info/LICENSE
plrc-0.1.0.dist-info/WHEEL
plrc-0.1.0.dist-info/METADATA
plrc-0.1.0.dist-info/RECORD
