Metadata-Version: 2.1
Name: plrc
Version: 0.1.0
Summary: Polaris language compiler.
Home-page: https://github.com/an-dyy/Polaris
Author: andy
Author-email: andy.development@protonmail.com
Requires-Python: >=3.10,<4.0
Classifier: Programming Language :: Python :: 3
Classifier: Programming Language :: Python :: 3.10
Requires-Dist: astpretty (>=3.0.0,<4.0.0)
Requires-Dist: black (>=22.6.0,<23.0.0)
Requires-Dist: isort (>=5.10.1,<6.0.0)
Requires-Dist: lark (>=1.1.2,<2.0.0)
